Workbook

Sheet 00_README
A1: Project NoeMI ROI Calculator Template
A2: Field | B2: Value | C2: Notes
A3: deployment_name | B3: Template deployment | C3: Rename per client or internal program copy.
A4: client_name | B4: Template client | C4: Use example data only in the public template.
A5: owner | B5: Program owner | C5: Set the accountable operator or Accelerator.
A6: currency | B6: USD | C6: Use one currency per workbook copy.
A7: review_cadence | B7: Monthly | C7: Review with operators and executive stakeholders.
A8: baseline_last_approved_on | B8: 2026-04-03 | C8: Refresh whenever assumptions change.
A9: generated_on | B9: 2026-04-03 | C9: Workbook artifact generated from repo source.
A11: What this workbook measures | B11: Conservative labor-cost avoidance and net ROI | C11: Only count validated, explainable executions.
A12: What this workbook does not measure | B12: Speculative value claims or unlogged work | C12: Do not use unverifiable task counts.
A13: Operating rule | B13: Evidence first | C13: Every included execution should have a traceable source and evidence reference.
A14: Operating rule | B14: Conservative valuation | C14: Prefer the lower credible baseline when estimates are uncertain.
... A26: Publishing checklist | B26: Ready for 'Make a copy' workflow | C26: Use the workbook upload to create the public Google Sheets template.

Sheet 01_ASSUMPTIONS
A1: role_id | B1: human_role | C1: loaded_hourly_rate | D1: rate_source | E1: approved_by | F1: approved_on | G1: notes
A2: engineering_manager | B2: Engineering Manager | C2: 120 | D2: Illustrative blended internal rate | E2: Accelerator lead | F2: 2026-04-03 | G2: Replace with approved deployment rate.
A3: it_ops_engineer | B3: IT Operations Engineer | C3: 85 | D3: Illustrative blended internal rate | E3: Accelerator lead | F3: 2026-04-03 | G3: Replace with approved deployment rate.
A4: knowledge_worker | B4: Knowledge Worker | C4: 70 | D4: Illustrative blended internal rate | E4: Accelerator lead | F4: 2026-04-03 | G4: Replace with approved deployment rate.
A5: marketing_manager | B5: Marketing Manager | C5: 75 | D5: Illustrative blended internal rate | E5: Accelerator lead | F5: 2026-04-03 | G5: Replace with approved deployment rate.
A6: content_producer | B6: Content Producer | C6: 65 | D6: Illustrative blended internal rate | E6: Accelerator lead | F6: 2026-04-03 | G6: Replace with approved deployment rate.

Sheet 02_TASK_CATALOG
A1: task_id | B1: agent_persona | C1: task_name | D1: business_function | E1: human_role_owner | F1: human_baseline_minutes | G1: human_review_minutes | H1: exception_minutes | I1: evidence_required | J1: approved_for_roi | K1: baseline_owner | L1: baseline_last_reviewed
A2: gatekeeper_pr_triage | B2: engineering/gatekeeper | C2: Triage pull request risk | D2: engineering | E2: engineering_manager | F2: 20 | G2: 5 | H2: 2 | I2: Structured PR report plus trace_id | J2: TRUE | K2: Accelerator lead | L2: 2026-04-03
A3: knowledge_manager_internal_answer | B3: operations/knowledge-manager | C3: Answer internal policy question | D3: operations | E3: knowledge_worker | F3: 15 | G3: 4 | H3: 1 | I3: Knowledge answer output plus source refs | J3: TRUE | K3: Accelerator lead | L3: 2026-04-03
A4: linux_daily_health_check | B4: infrastructure/linux | C4: Run daily health check and summarize | D4: operations | E4: it_ops_engineer | F4: 25 | G4: 5 | H4: 2 | I4: Health summary plus host trace | J4: TRUE | K4: Accelerator lead | L4: 2026-04-03
A5: seo_metadata_generation | B5: marketing/seo-strategist | C5: Draft SEO metadata package | D5: marketing | E5: marketing_manager | F5: 30 | G5: 8 | H5: 3 | I5: Metadata package plus campaign trace | J5: TRUE | K5: Accelerator lead | L5: 2026-04-03
A6: video_content_packaging | B6: marketing/video-content-manager | C6: Package rough cut into publishable asset set | D6: marketing | E6: content_producer | F6: 45 | G6: 12 | H6: 5 | I6: Packaging output plus content trace | J6: TRUE | K6: Accelerator lead | L6: 2026-04-03

Sheet 03_EXECUTION_LOG
A1: execution_id | B1: timestamp_utc | C1: tenant_id | D1: agent_persona | E1: task_id | F1: status | G1: trace_id | H1: quantity | I1: review_required | J1: evidence_ref | K1: source_system | L1: notes
A2: sample-exec-001 | B2: 2026-04-01T09:15:00Z | C2: tenant-template | D2: engineering/gatekeeper | E2: gatekeeper_pr_triage | F2: success | G2: trace-001 | H2: 1 | I2: FALSE | J2: github:pr/123 | K2: github | L2: Example execution row
A3: sample-exec-002 | B3: 2026-04-03T11:00:00Z | C3: tenant-template | D3: operations/knowledge-manager | E3: knowledge_manager_internal_answer | F3: success | G3: trace-002 | H3: 3 | I3: FALSE | J3: docs:policy/remote-work | K3: n8n | L3: Example execution row
A4: sample-exec-003 | B4: 2026-04-05T07:30:00Z | C4: tenant-template | D4: infrastructure/linux | E4: linux_daily_health_check | F4: success | G4: trace-003 | H4: 1 | I4: FALSE | J4: loki:health-check/445 | K4: loki | L4: Example execution row
A5: sample-exec-004 | B5: 2026-04-06T14:20:00Z | C5: tenant-template | D5: marketing/seo-strategist | E5: seo_metadata_generation | F5: success | G5: trace-004 | H5: 2 | I5: TRUE | J5: drive:seo-brief/2026-04 | K5: google-drive | L5: Example execution row
A6: sample-exec-005 | B6: 2026-04-08T16:45:00Z | C6: tenant-template | D6: marketing/video-content-manager | E6: video_content_packaging | F6: failed | G6: trace-005 | H6: 1 | I6: TRUE | J6: drive:video-job/2026-04 | K6: n8n | L6: Failed example row should be excluded

Sheet 04_ROI_AUDIT
A1: execution_id | B1: month | C1: task_id | D1: human_role_owner | E1: baseline_minutes | F1: review_minutes | G1: exception_minutes | H1: net_minutes_saved | I1: hours_saved | J1: hourly_rate | K1: gross_cost_avoidance | L1: included_in_roi | M1: exclusion_reason | N1: confidence_band | O1: can_this_be_explained_to_a_cfo
A2: =IF('03_EXECUTION_LOG'!A2="","",'03_EXECUTION_LOG'!A2) | B2: =IF('03_EXECUTION_LOG'!B2="","",LEFT('03_EXECUTION_LOG'!B2,7)) | C2: =IF('03_EXECUTION_LOG'!E2="","",'03_EXECUTION_LOG'!E2) | D2: =IF(C2="","",INDEX('02_TASK_CATALOG'!E:E,MATCH(C2,'02_TASK_CATALOG'!A:A,0))) | E2: =IF(C2="","",INDEX('02_TASK_CATALOG'!F:F,MATCH(C2,'02_TASK_CATALOG'!A:A,0))) -> 0 | F2: =IF(C2="","",INDEX('02_TASK_CATALOG'!G:G,MATCH(C2,'02_TASK_CATALOG'!A:A,0))) -> 0 | G2: =IF(C2="","",INDEX('02_TASK_CATALOG'!H:H,MATCH(C2,'02_TASK_CATALOG'!A:A,0))) -> 0 | H2: =IF(A2="","",MAX(0,E2-F2-G2)) -> 0 | I2: =IF(A2="","",H2*IF('03_EXECUTION_LOG'!H2="",1,'03_EXECUTION_LOG'!H2)/60) -> 0 | J2: =IF(D2="","",INDEX('01_ASSUMPTIONS'!C:C,MATCH(D2,'01_ASSUMPTIONS'!A:A,0))) -> 0 | K2: =IF(OR(A2="",L2<>TRUE),0,I2*J2) -> 0 | L2: =IF(A2="","",AND('03_EXECUTION_LOG'!F2="success",INDEX('02_TASK_CATALOG'!J:J,MATCH(C2,'02_TASK_CATALOG'!A:A,0))=TRUE,H2>0,J2>0,'03_EXECUTION_LOG'!J2<>"")) -> FALSE | M2: =IF(A2="","",IF('03_EXECUTION_LOG'!F2<>"success","non-success status",IF(INDEX('02_TASK_CATALOG'!J:J,MATCH(C2,'02_TASK_CATALOG'!A:A,0))<>TRUE,"task not approved",IF(H2<=0,"no net time saved",IF(J2<=0,"missing labor rate",IF('03_EXECUTION_LOG'!J2="","missing evidence","")))))) | N2: =IF(A2="","",IF(AND(L2=TRUE,'03_EXECUTION_LOG'!I2=FALSE),"high",IF(AND(L2=TRUE,'03_EXECUTION_LOG'!I2=TRUE),"medium","low"))) | O2: =IF(A2="","",IF(AND(L2=TRUE,'03_EXECUTION_LOG'!J2<>""),"yes","needs-review"))
A3: =IF('03_EXECUTION_LOG'!A3="","",'03_EXECUTION_LOG'!A3) | B3: =IF('03_EXECUTION_LOG'!B3="","",LEFT('03_EXECUTION_LOG'!B3,7)) | C3: =IF('03_EXECUTION_LOG'!E3="","",'03_EXECUTION_LOG'!E3) | D3: =IF(C3="","",INDEX('02_TASK_CATALOG'!E:E,MATCH(C3,'02_TASK_CATALOG'!A:A,0))) | E3: =IF(C3="","",INDEX('02_TASK_CATALOG'!F:F,MATCH(C3,'02_TASK_CATALOG'!A:A,0))) -> 0 | F3: =IF(C3="","",INDEX('02_TASK_CATALOG'!G:G,MATCH(C3,'02_TASK_CATALOG'!A:A,0))) -> 0 | G3: =IF(C3="","",INDEX('02_TASK_CATALOG'!H:H,MATCH(C3,'02_TASK_CATALOG'!A:A,0))) -> 0 | H3: =IF(A3="","",MAX(0,E3-F3-G3)) -> 0 | I3: =IF(A3="","",H3*IF('03_EXECUTION_LOG'!H3="",1,'03_EXECUTION_LOG'!H3)/60) -> 0 | J3: =IF(D3="","",INDEX('01_ASSUMPTIONS'!C:C,MATCH(D3,'01_ASSUMPTIONS'!A:A,0))) -> 0 | K3: =IF(OR(A3="",L3<>TRUE),0,I3*J3) -> 0 | L3: =IF(A3="","",AND('03_EXECUTION_LOG'!F3="success",INDEX('02_TASK_CATALOG'!J:J,MATCH(C3,'02_TASK_CATALOG'!A:A,0))=TRUE,H3>0,J3>0,'03_EXECUTION_LOG'!J3<>"")) -> FALSE | M3: =IF(A3="","",IF('03_EXECUTION_LOG'!F3<>"success","non-success status",IF(INDEX('02_TASK_CATALOG'!J:J,MATCH(C3,'02_TASK_CATALOG'!A:A,0))<>TRUE,"task not approved",IF(H3<=0,"no net time saved",IF(J3<=0,"missing labor rate",IF('03_EXECUTION_LOG'!J3="","missing evidence","")))))) | N3: =IF(A3="","",IF(AND(L3=TRUE,'03_EXECUTION_LOG'!I3=FALSE),"high",IF(AND(L3=TRUE,'03_EXECUTION_LOG'!I3=TRUE),"medium","low"))) | O3: =IF(A3="","",IF(AND(L3=TRUE,'03_EXECUTION_LOG'!J3<>""),"yes","needs-review"))
A4: =IF('03_EXECUTION_LOG'!A4="","",'03_EXECUTION_LOG'!A4) | B4: =IF('03_EXECUTION_LOG'!B4="","",LEFT('03_EXECUTION_LOG'!B4,7)) | C4: =IF('03_EXECUTION_LOG'!E4="","",'03_EXECUTION_LOG'!E4) | D4: =IF(C4="","",INDEX('02_TASK_CATALOG'!E:E,MATCH(C4,'02_TASK_CATALOG'!A:A,0))) | E4: =IF(C4="","",INDEX('02_TASK_CATALOG'!F:F,MATCH(C4,'02_TASK_CATALOG'!A:A,0))) -> 0 | F4: =IF(C4="","",INDEX('02_TASK_CATALOG'!G:G,MATCH(C4,'02_TASK_CATALOG'!A:A,0))) -> 0 | G4: =IF(C4="","",INDEX('02_TASK_CATALOG'!H:H,MATCH(C4,'02_TASK_CATALOG'!A:A,0))) -> 0 | H4: =IF(A4="","",MAX(0,E4-F4-G4)) -> 0 | I4: =IF(A4="","",H4*IF('03_EXECUTION_LOG'!H4="",1,'03_EXECUTION_LOG'!H4)/60) -> 0 | J4: =IF(D4="","",INDEX('01_ASSUMPTIONS'!C:C,MATCH(D4,'01_ASSUMPTIONS'!A:A,0))) -> 0 | K4: =IF(OR(A4="",L4<>TRUE),0,I4*J4) -> 0 | L4: =IF(A4="","",AND('03_EXECUTION_LOG'!F4="success",INDEX('02_TASK_CATALOG'!J:J,MATCH(C4,'02_TASK_CATALOG'!A:A,0))=TRUE,H4>0,J4>0,'03_EXECUTION_LOG'!J4<>"")) -> FALSE | M4: =IF(A4="","",IF('03_EXECUTION_LOG'!F4<>"success","non-success status",IF(INDEX('02_TASK_CATALOG'!J:J,MATCH(C4,'02_TASK_CATALOG'!A:A,0))<>TRUE,"task not approved",IF(H4<=0,"no net time saved",IF(J4<=0,"missing labor rate",IF('03_EXECUTION_LOG'!J4="","missing evidence","")))))) | N4: =IF(A4="","",IF(AND(L4=TRUE,'03_EXECUTION_LOG'!I4=FALSE),"high",IF(AND(L4=TRUE,'03_EXECUTION_LOG'!I4=TRUE),"medium","low"))) | O4: =IF(A4="","",IF(AND(L4=TRUE,'03_EXECUTION_LOG'!J4<>""),"yes","needs-review"))
A5: =IF('03_EXECUTION_LOG'!A5="","",'03_EXECUTION_LOG'!A5) | B5: =IF('03_EXECUTION_LOG'!B5="","",LEFT('03_EXECUTION_LOG'!B5,7)) | C5: =IF('03_EXECUTION_LOG'!E5="","",'03_EXECUTION_LOG'!E5) | D5: =IF(C5="","",INDEX('02_TASK_CATALOG'!E:E,MATCH(C5,'02_TASK_CATALOG'!A:A,0))) | E5: =IF(C5="","",INDEX('02_TASK_CATALOG'!F:F,MATCH(C5,'02_TASK_CATALOG'!A:A,0))) -> 0 | F5: =IF(C5="","",INDEX('02_TASK_CATALOG'!G:G,MATCH(C5,'02_TASK_CATALOG'!A:A,0))) -> 0 | G5: =IF(C5="","",INDEX('02_TASK_CATALOG'!H:H,MATCH(C5,'02_TASK_CATALOG'!A:A,0))) -> 0 | H5: =IF(A5="","",MAX(0,E5-F5-G5)) -> 0 | I5: =IF(A5="","",H5*IF('03_EXECUTION_LOG'!H5="",1,'03_EXECUTION_LOG'!H5)/60) -> 0 | J5: =IF(D5="","",INDEX('01_ASSUMPTIONS'!C:C,MATCH(D5,'01_ASSUMPTIONS'!A:A,0))) -> 0 | K5: =IF(OR(A5="",L5<>TRUE),0,I5*J5) -> 0 | L5: =IF(A5="","",AND('03_EXECUTION_LOG'!F5="success",INDEX('02_TASK_CATALOG'!J:J,MATCH(C5,'02_TASK_CATALOG'!A:A,0))=TRUE,H5>0,J5>0,'03_EXECUTION_LOG'!J5<>"")) -> FALSE | M5: =IF(A5="","",IF('03_EXECUTION_LOG'!F5<>"success","non-success status",IF(INDEX('02_TASK_CATALOG'!J:J,MATCH(C5,'02_TASK_CATALOG'!A:A,0))<>TRUE,"task not approved",IF(H5<=0,"no net time saved",IF(J5<=0,"missing labor rate",IF('03_EXECUTION_LOG'!J5="","missing evidence","")))))) | N5: =IF(A5="","",IF(AND(L5=TRUE,'03_EXECUTION_LOG'!I5=FALSE),"high",IF(AND(L5=TRUE,'03_EXECUTION_LOG'!I5=TRUE),"medium","low"))) | O5: =IF(A5="","",IF(AND(L5=TRUE,'03_EXECUTION_LOG'!J5<>""),"yes","needs-review"))
A6: =IF('03_EXECUTION_LOG'!A6="","",'03_EXECUTION_LOG'!A6) | B6: =IF('03_EXECUTION_LOG'!B6="","",LEFT('03_EXECUTION_LOG'!B6,7)) | C6: =IF('03_EXECUTION_LOG'!E6="","",'03_EXECUTION_LOG'!E6) | D6: =IF(C6="","",INDEX('02_TASK_CATALOG'!E:E,MATCH(C6,'02_TASK_CATALOG'!A:A,0))) | E6: =IF(C6="","",INDEX('02_TASK_CATALOG'!F:F,MATCH(C6,'02_TASK_CATALOG'!A:A,0))) -> 0 | F6: =IF(C6="","",INDEX('02_TASK_CATALOG'!G:G,MATCH(C6,'02_TASK_CATALOG'!A:A,0))) -> 0 | G6: =IF(C6="","",INDEX('02_TASK_CATALOG'!H:H,MATCH(C6,'02_TASK_CATALOG'!A:A,0))) -> 0 | H6: =IF(A6="","",MAX(0,E6-F6-G6)) -> 0 | I6: =IF(A6="","",H6*IF('03_EXECUTION_LOG'!H6="",1,'03_EXECUTION_LOG'!H6)/60) -> 0 | J6: =IF(D6="","",INDEX('01_ASSUMPTIONS'!C:C,MATCH(D6,'01_ASSUMPTIONS'!A:A,0))) -> 0 | K6: =IF(OR(A6="",L6<>TRUE),0,I6*J6) -> 0 | L6: =IF(A6="","",AND('03_EXECUTION_LOG'!F6="success",INDEX('02_TASK_CATALOG'!J:J,MATCH(C6,'02_TASK_CATALOG'!A:A,0))=TRUE,H6>0,J6>0,'03_EXECUTION_LOG'!J6<>"")) -> FALSE | M6: =IF(A6="","",IF('03_EXECUTION_LOG'!F6<>"success","non-success status",IF(INDEX('02_TASK_CATALOG'!J:J,MATCH(C6,'02_TASK_CATALOG'!A:A,0))<>TRUE,"task not approved",IF(H6<=0,"no net time saved",IF(J6<=0,"missing labor rate",IF('03_EXECUTION_LOG'!J6="","missing evidence","")))))) | N6: =IF(A6="","",IF(AND(L6=TRUE,'03_EXECUTION_LOG'!I6=FALSE),"high",IF(AND(L6=TRUE,'03_EXECUTION_LOG'!I6=TRUE),"medium","low"))) | O6: =IF(A6="","",IF(AND(L6=TRUE,'03_EXECUTION_LOG'!J6<>""),"yes","needs-review"))
A7: =IF('03_EXECUTION_LOG'!A7="","",'03_EXECUTION_LOG'!A7) | B7: =IF('03_EXECUTION_LOG'!B7="","",LEFT('03_EXECUTION_LOG'!B7,7)) | C7: =IF('03_EXECUTION_LOG'!E7="","",'03_EXECUTION_LOG'!E7) | D7: =IF(C7="","",INDEX('02_TASK_CATALOG'!E:E,MATCH(C7,'02_TASK_CATALOG'!A:A,0))) | E7: =IF(C7="","",INDEX('02_TASK_CATALOG'!F:F,MATCH(C7,'02_TASK_CATALOG'!A:A,0))) -> 0 | F7: =IF(C7="","",INDEX('02_TASK_CATALOG'!G:G,MATCH(C7,'02_TASK_CATALOG'!A:A,0))) -> 0 | G7: =IF(C7="","",INDEX('02_TASK_CATALOG'!H:H,MATCH(C7,'02_TASK_CATALOG'!A:A,0))) -> 0 | H7: =IF(A7="","",MAX(0,E7-F7-G7)) -> 0 | I7: =IF(A7="","",H7*IF('03_EXECUTION_LOG'!H7="",1,'03_EXECUTION_LOG'!H7)/60) -> 0 | J7: =IF(D7="","",INDEX('01_ASSUMPTIONS'!C:C,MATCH(D7,'01_ASSUMPTIONS'!A:A,0))) -> 0 | K7: =IF(OR(A7="",L7<>TRUE),0,I7*J7) -> 0 | L7: =IF(A7="","",AND('03_EXECUTION_LOG'!F7="success",INDEX('02_TASK_CATALOG'!J:J,MATCH(C7,'02_TASK_CATALOG'!A:A,0))=TRUE,H7>0,J7>0,'03_EXECUTION_LOG'!J7<>"")) -> FALSE | M7: =IF(A7="","",IF('03_EXECUTION_LOG'!F7<>"success","non-success status",IF(INDEX('02_TASK_CATALOG'!J:J,MATCH(C7,'02_TASK_CATALOG'!A:A,0))<>TRUE,"task not approved",IF(H7<=0,"no net time saved",IF(J7<=0,"missing labor rate",IF('03_EXECUTION_LOG'!J7="","missing evidence","")))))) | N7: =IF(A7="","",IF(AND(L7=TRUE,'03_EXECUTION_LOG'!I7=FALSE),"high",IF(AND(L7=TRUE,'03_EXECUTION_LOG'!I7=TRUE),"medium","low"))) | O7: =IF(A7="","",IF(AND(L7=TRUE,'03_EXECUTION_LOG'!J7<>""),"yes","needs-review"))
A8: =IF('03_EXECUTION_LOG'!A8="","",'03_EXECUTION_LOG'!A8) | B8: =IF('03_EXECUTION_LOG'!B8="","",LEFT('03_EXECUTION_LOG'!B8,7)) | C8: =IF('03_EXECUTION_LOG'!E8="","",'03_EXECUTION_LOG'!E8) | D8: =IF(C8="","",INDEX('02_TASK_CATALOG'!E:E,MATCH(C8,'02_TASK_CATALOG'!A:A,0))) | E8: =IF(C8="","",INDEX('02_TASK_CATALOG'!F:F,MATCH(C8,'02_TASK_CATALOG'!A:A,0))) -> 0 | F8: =IF(C8="","",INDEX('02_TASK_CATALOG'!G:G,MATCH(C8,'02_TASK_CATALOG'!A:A,0))) -> 0 | G8: =IF(C8="","",INDEX('02_TASK_CATALOG'!H:H,MATCH(C8,'02_TASK_CATALOG'!A:A,0))) -> 0 | H8: =IF(A8="","",MAX(0,E8-F8-G8)) -> 0 | I8: =IF(A8="","",H8*IF('03_EXECUTION_LOG'!H8="",1,'03_EXECUTION_LOG'!H8)/60) -> 0 | J8: =IF(D8="","",INDEX('01_ASSUMPTIONS'!C:C,MATCH(D8,'01_ASSUMPTIONS'!A:A,0))) -> 0 | K8: =IF(OR(A8="",L8<>TRUE),0,I8*J8) -> 0 | L8: =IF(A8="","",AND('03_EXECUTION_LOG'!F8="success",INDEX('02_TASK_CATALOG'!J:J,MATCH(C8,'02_TASK_CATALOG'!A:A,0))=TRUE,H8>0,J8>0,'03_EXECUTION_LOG'!J8<>"")) -> FALSE | M8: =IF(A8="","",IF('03_EXECUTION_LOG'!F8<>"success","non-success status",IF(INDEX('02_TASK_CATALOG'!J:J,MATCH(C8,'02_TASK_CATALOG'!A:A,0))<>TRUE,"task not approved",IF(H8<=0,"no net time saved",IF(J8<=0,"missing labor rate",IF('03_EXECUTION_LOG'!J8="","missing evidence","")))))) | N8: =IF(A8="","",IF(AND(L8=TRUE,'03_EXECUTION_LOG'!I8=FALSE),"high",IF(AND(L8=TRUE,'03_EXECUTION_LOG'!I8=TRUE),"medium","low"))) | O8: =IF(A8="","",IF(AND(L8=TRUE,'03_EXECUTION_LOG'!J8<>""),"yes","needs-review"))
A9: =IF('03_EXECUTION_LOG'!A9="","",'03_EXECUTION_LOG'!A9) | B9: =IF('03_EXECUTION_LOG'!B9="","",LEFT('03_EXECUTION_LOG'!B9,7)) | C9: =IF('03_EXECUTION_LOG'!E9="","",'03_EXECUTION_LOG'!E9) | D9: =IF(C9="","",INDEX('02_TASK_CATALOG'!E:E,MATCH(C9,'02_TASK_CATALOG'!A:A,0))) | E9: =IF(C9="","",INDEX('02_TASK_CATALOG'!F:F,MATCH(C9,'02_TASK_CATALOG'!A:A,0))) -> 0 | F9: =IF(C9="","",INDEX('02_TASK_CATALOG'!G:G,MATCH(C9,'02_TASK_CATALOG'!A:A,0))) -> 0 | G9: =IF(C9="","",INDEX('02_TASK_CATALOG'!H:H,MATCH(C9,'02_TASK_CATALOG'!A:A,0))) -> 0 | H9: =IF(A9="","",MAX(0,E9-F9-G9)) -> 0 | I9: =IF(A9="","",H9*IF('03_EXECUTION_LOG'!H9="",1,'03_EXECUTION_LOG'!H9)/60) -> 0 | J9: =IF(D9="","",INDEX('01_ASSUMPTIONS'!C:C,MATCH(D9,'01_ASSUMPTIONS'!A:A,0))) -> 0 | K9: =IF(OR(A9="",L9<>TRUE),0,I9*J9) -> 0 | L9: =IF(A9="","",AND('03_EXECUTION_LOG'!F9="success",INDEX('02_TASK_CATALOG'!J:J,MATCH(C9,'02_TASK_CATALOG'!A:A,0))=TRUE,H9>0,J9>0,'03_EXECUTION_LOG'!J9<>"")) -> FALSE | M9: =IF(A9="","",IF('03_EXECUTION_LOG'!F9<>"success","non-success status",IF(INDEX('02_TASK_CATALOG'!J:J,MATCH(C9,'02_TASK_CATALOG'!A:A,0))<>TRUE,"task not approved",IF(H9<=0,"no net time saved",IF(J9<=0,"missing labor rate",IF('03_EXECUTION_LOG'!J9="","missing evidence","")))))) | N9: =IF(A9="","",IF(AND(L9=TRUE,'03_EXECUTION_LOG'!I9=FALSE),"high",IF(AND(L9=TRUE,'03_EXECUTION_LOG'!I9=TRUE),"medium","low"))) | O9: =IF(A9="","",IF(AND(L9=TRUE,'03_EXECUTION_LOG'!J9<>""),"yes","needs-review"))
A10: =IF('03_EXECUTION_LOG'!A10="","",'03_EXECUTION_LOG'!A10) | B10: =IF('03_EXECUTION_LOG'!B10="","",LEFT('03_EXECUTION_LOG'!B10,7)) | C10: =IF('03_EXECUTION_LOG'!E10="","",'03_EXECUTION_LOG'!E10) | D10: =IF(C10="","",INDEX('02_TASK_CATALOG'!E:E,MATCH(C10,'02_TASK_CATALOG'!A:A,0))) | E10: =IF(C10="","",INDEX('02_TASK_CATALOG'!F:F,MATCH(C10,'02_TASK_CATALOG'!A:A,0))) -> 0 | F10: =IF(C10="","",INDEX('02_TASK_CATALOG'!G:G,MATCH(C10,'02_TASK_CATALOG'!A:A,0))) -> 0 | G10: =IF(C10="","",INDEX('02_TASK_CATALOG'!H:H,MATCH(C10,'02_TASK_CATALOG'!A:A,0))) -> 0 | H10: =IF(A10="","",MAX(0,E10-F10-G10)) -> 0 | I10: =IF(A10="","",H10*IF('03_EXECUTION_LOG'!H10="",1,'03_EXECUTION_LOG'!H10)/60) -> 0 | J10: =IF(D10="","",INDEX('01_ASSUMPTIONS'!C:C,MATCH(D10,'01_ASSUMPTIONS'!A:A,0))) -> 0 | K10: =IF(OR(A10="",L10<>TRUE),0,I10*J10) -> 0 | L10: =IF(A10="","",AND('03_EXECUTION_LOG'!F10="success",INDEX('02_TASK_CATALOG'!J:J,MATCH(C10,'02_TASK_CATALOG'!A:A,0))=TRUE,H10>0,J10>0,'03_EXECUTION_LOG'!J10<>"")) -> FALSE | M10: =IF(A10="","",IF('03_EXECUTION_LOG'!F10<>"success","non-success status",IF(INDEX('02_TASK_CATALOG'!J:J,MATCH(C10,'02_TASK_CATALOG'!A:A,0))<>TRUE,"task not approved",IF(H10<=0,"no net time saved",IF(J10<=0,"missing labor rate",IF('03_EXECUTION_LOG'!J10="","missing evidence","")))))) | N10: =IF(A10="","",IF(AND(L10=TRUE,'03_EXECUTION_LOG'!I10=FALSE),"high",IF(AND(L10=TRUE,'03_EXECUTION_LOG'!I10=TRUE),"medium","low"))) | O10: =IF(A10="","",IF(AND(L10=TRUE,'03_EXECUTION_LOG'!J10<>""),"yes","needs-review"))
A11: =IF('03_EXECUTION_LOG'!A11="","",'03_EXECUTION_LOG'!A11) | B11: =IF('03_EXECUTION_LOG'!B11="","",LEFT('03_EXECUTION_LOG'!B11,7)) | C11: =IF('03_EXECUTION_LOG'!E11="","",'03_EXECUTION_LOG'!E11) | D11: =IF(C11="","",INDEX('02_TASK_CATALOG'!E:E,MATCH(C11,'02_TASK_CATALOG'!A:A,0))) | E11: =IF(C11="","",INDEX('02_TASK_CATALOG'!F:F,MATCH(C11,'02_TASK_CATALOG'!A:A,0))) -> 0 | F11: =IF(C11="","",INDEX('02_TASK_CATALOG'!G:G,MATCH(C11,'02_TASK_CATALOG'!A:A,0))) -> 0 | G11: =IF(C11="","",INDEX('02_TASK_CATALOG'!H:H,MATCH(C11,'02_TASK_CATALOG'!A:A,0))) -> 0 | H11: =IF(A11="","",MAX(0,E11-F11-G11)) -> 0 | I11: =IF(A11="","",H11*IF('03_EXECUTION_LOG'!H11="",1,'03_EXECUTION_LOG'!H11)/60) -> 0 | J11: =IF(D11="","",INDEX('01_ASSUMPTIONS'!C:C,MATCH(D11,'01_ASSUMPTIONS'!A:A,0))) -> 0 | K11: =IF(OR(A11="",L11<>TRUE),0,I11*J11) -> 0 | L11: =IF(A11="","",AND('03_EXECUTION_LOG'!F11="success",INDEX('02_TASK_CATALOG'!J:J,MATCH(C11,'02_TASK_CATALOG'!A:A,0))=TRUE,H11>0,J11>0,'03_EXECUTION_LOG'!J11<>"")) -> FALSE | M11: =IF(A11="","",IF('03_EXECUTION_LOG'!F11<>"success","non-success status",IF(INDEX('02_TASK_CATALOG'!J:J,MATCH(C11,'02_TASK_CATALOG'!A:A,0))<>TRUE,"task not approved",IF(H11<=0,"no net time saved",IF(J11<=0,"missing labor rate",IF('03_EXECUTION_LOG'!J11="","missing evidence","")))))) | N11: =IF(A11="","",IF(AND(L11=TRUE,'03_EXECUTION_LOG'!I11=FALSE),"high",IF(AND(L11=TRUE,'03_EXECUTION_LOG'!I11=TRUE),"medium","low"))) | O11: =IF(A11="","",IF(AND(L11=TRUE,'03_EXECUTION_LOG'!J11<>""),"yes","needs-review"))
A12: =IF('03_EXECUTION_LOG'!A12="","",'03_EXECUTION_LOG'!A12) | B12: =IF('03_EXECUTION_LOG'!B12="","",LEFT('03_EXECUTION_LOG'!B12,7)) | C12: =IF('03_EXECUTION_LOG'!E12="","",'03_EXECUTION_LOG'!E12) | D12: =IF(C12="","",INDEX('02_TASK_CATALOG'!E:E,MATCH(C12,'02_TASK_CATALOG'!A:A,0))) | E12: =IF(C12="","",INDEX('02_TASK_CATALOG'!F:F,MATCH(C12,'02_TASK_CATALOG'!A:A,0))) -> 0 | F12: =IF(C12="","",INDEX('02_TASK_CATALOG'!G:G,MATCH(C12,'02_TASK_CATALOG'!A:A,0))) -> 0 | G12: =IF(C12="","",INDEX('02_TASK_CATALOG'!H:H,MATCH(C12,'02_TASK_CATALOG'!A:A,0))) -> 0 | H12: =IF(A12="","",MAX(0,E12-F12-G12)) -> 0 | I12: =IF(A12="","",H12*IF('03_EXECUTION_LOG'!H12="",1,'03_EXECUTION_LOG'!H12)/60) -> 0 | J12: =IF(D12="","",INDEX('01_ASSUMPTIONS'!C:C,MATCH(D12,'01_ASSUMPTIONS'!A:A,0))) -> 0 | K12: =IF(OR(A12="",L12<>TRUE),0,I12*J12) -> 0 | L12: =IF(A12="","",AND('03_EXECUTION_LOG'!F12="success",INDEX('02_TASK_CATALOG'!J:J,MATCH(C12,'02_TASK_CATALOG'!A:A,0))=TRUE,H12>0,J12>0,'03_EXECUTION_LOG'!J12<>"")) -> FALSE | M12: =IF(A12="","",IF('03_EXECUTION_LOG'!F12<>"success","non-success status",IF(INDEX('02_TASK_CATALOG'!J:J,MATCH(C12,'02_TASK_CATALOG'!A:A,0))<>TRUE,"task not approved",IF(H12<=0,"no net time saved",IF(J12<=0,"missing labor rate",IF('03_EXECUTION_LOG'!J12="","missing evidence","")))))) | N12: =IF(A12="","",IF(AND(L12=TRUE,'03_EXECUTION_LOG'!I12=FALSE),"high",IF(AND(L12=TRUE,'03_EXECUTION_LOG'!I12=TRUE),"medium","low"))) | O12: =IF(A12="","",IF(AND(L12=TRUE,'03_EXECUTION_LOG'!J12<>""),"yes","needs-review"))
A13: =IF('03_EXECUTION_LOG'!A13="","",'03_EXECUTION_LOG'!A13) | B13: =IF('03_EXECUTION_LOG'!B13="","",LEFT('03_EXECUTION_LOG'!B13,7)) | C13: =IF('03_EXECUTION_LOG'!E13="","",'03_EXECUTION_LOG'!E13) | D13: =IF(C13="","",INDEX('02_TASK_CATALOG'!E:E,MATCH(C13,'02_TASK_CATALOG'!A:A,0))) | E13: =IF(C13="","",INDEX('02_TASK_CATALOG'!F:F,MATCH(C13,'02_TASK_CATALOG'!A:A,0))) -> 0 | F13: =IF(C13="","",INDEX('02_TASK_CATALOG'!G:G,MATCH(C13,'02_TASK_CATALOG'!A:A,0))) -> 0 | G13: =IF(C13="","",INDEX('02_TASK_CATALOG'!H:H,MATCH(C13,'02_TASK_CATALOG'!A:A,0))) -> 0 | H13: =IF(A13="","",MAX(0,E13-F13-G13)) -> 0 | I13: =IF(A13="","",H13*IF('03_EXECUTION_LOG'!H13="",1,'03_EXECUTION_LOG'!H13)/60) -> 0 | J13: =IF(D13="","",INDEX('01_ASSUMPTIONS'!C:C,MATCH(D13,'01_ASSUMPTIONS'!A:A,0))) -> 0 | K13: =IF(OR(A13="",L13<>TRUE),0,I13*J13) -> 0 | L13: =IF(A13="","",AND('03_EXECUTION_LOG'!F13="success",INDEX('02_TASK_CATALOG'!J:J,MATCH(C13,'02_TASK_CATALOG'!A:A,0))=TRUE,H13>0,J13>0,'03_EXECUTION_LOG'!J13<>"")) -> FALSE | M13: =IF(A13="","",IF('03_EXECUTION_LOG'!F13<>"success","non-success status",IF(INDEX('02_TASK_CATALOG'!J:J,MATCH(C13,'02_TASK_CATALOG'!A:A,0))<>TRUE,"task not approved",IF(H13<=0,"no net time saved",IF(J13<=0,"missing labor rate",IF('03_EXECUTION_LOG'!J13="","missing evidence","")))))) | N13: =IF(A13="","",IF(AND(L13=TRUE,'03_EXECUTION_LOG'!I13=FALSE),"high",IF(AND(L13=TRUE,'03_EXECUTION_LOG'!I13=TRUE),"medium","low"))) | O13: =IF(A13="","",IF(AND(L13=TRUE,'03_EXECUTION_LOG'!J13<>""),"yes","needs-review"))
... A251: =IF('03_EXECUTION_LOG'!A251="","",'03_EXECUTION_LOG'!A251) | B251: =IF('03_EXECUTION_LOG'!B251="","",LEFT('03_EXECUTION_LOG'!B251,7)) | C251: =IF('03_EXECUTION_LOG'!E251="","",'03_EXECUTION_LOG'!E251) | D251: =IF(C251="","",INDEX('02_TASK_CATALOG'!E:E,MATCH(C251,'02_TASK_CATALOG'!A:A,0))) | E251: =IF(C251="","",INDEX('02_TASK_CATALOG'!F:F,MATCH(C251,'02_TASK_CATALOG'!A:A,0))) -> 0 | F251: =IF(C251="","",INDEX('02_TASK_CATALOG'!G:G,MATCH(C251,'02_TASK_CATALOG'!A:A,0))) -> 0 | G251: =IF(C251="","",INDEX('02_TASK_CATALOG'!H:H,MATCH(C251,'02_TASK_CATALOG'!A:A,0))) -> 0 | H251: =IF(A251="","",MAX(0,E251-F251-G251)) -> 0 | I251: =IF(A251="","",H251*IF('03_EXECUTION_LOG'!H251="",1,'03_EXECUTION_LOG'!H251)/60) -> 0 | J251: =IF(D251="","",INDEX('01_ASSUMPTIONS'!C:C,MATCH(D251,'01_ASSUMPTIONS'!A:A,0))) -> 0 | K251: =IF(OR(A251="",L251<>TRUE),0,I251*J251) -> 0 | L251: =IF(A251="","",AND('03_EXECUTION_LOG'!F251="success",INDEX('02_TASK_CATALOG'!J:J,MATCH(C251,'02_TASK_CATALOG'!A:A,0))=TRUE,H251>0,J251>0,'03_EXECUTION_LOG'!J251<>"")) -> FALSE | M251: =IF(A251="","",IF('03_EXECUTION_LOG'!F251<>"success","non-success status",IF(INDEX('02_TASK_CATALOG'!J:J,MATCH(C251,'02_TASK_CATALOG'!A:A,0))<>TRUE,"task not approved",IF(H251<=0,"no net time saved",IF(J251<=0,"missing labor rate",IF('03_EXECUTION_LOG'!J251="","missing evidence","")))))) | N251: =IF(A251="","",IF(AND(L251=TRUE,'03_EXECUTION_LOG'!I251=FALSE),"high",IF(AND(L251=TRUE,'03_EXECUTION_LOG'!I251=TRUE),"medium","low"))) | O251: =IF(A251="","",IF(AND(L251=TRUE,'03_EXECUTION_LOG'!J251<>""),"yes","needs-review"))

Sheet 05_INVESTMENT
A1: cost_id | B1: category | C1: cost_type | D1: description | E1: billing_frequency | F1: monthly_cost | G1: one_time_cost | H1: owner | I1: notes
A2: platform_infisical | B2: platform | C2: recurring | D2: SecretOps platform subscription | E2: monthly | F2: 250 | G2: 0 | H2: Ops lead | I2: Illustrative example row
A3: orchestrator_hosting | B3: platform | C3: recurring | D3: Container and orchestration hosting | E3: monthly | F3: 300 | G3: 0 | H3: Ops lead | I3: Illustrative example row
A4: rollout_enablement | B4: implementation | C4: one-time | D4: Initial workflow implementation and setup | E4: one-time | F4: 0 | G4: 4500 | H4: Program lead | I4: Illustrative example row
A5: managed_service_support | B5: managed_service | C5: recurring | D5: Ongoing operator tuning and support | E5: monthly | F5: 1200 | G5: 0 | H5: Service owner | I5: Illustrative example row
A6: training_enablement | B6: training | C6: one-time | D6: Governance and team enablement | E6: one-time | F6: 0 | G6: 1500 | H6: Learning owner | I6: Illustrative example row

Sheet 06_DASHBOARD
A1: Metric | B1: Value | C1: Notes
A2: selected_month | B2: 2026-04 | C2: Update this to review a different month.
A3: validated_executions | B3: =COUNTIFS('04_ROI_AUDIT'!L:L,TRUE,'04_ROI_AUDIT'!B:B,B2) -> 0 | C3: Included rows for the selected month.
A4: hours_saved_mtd | B4: =SUMIFS('04_ROI_AUDIT'!I:I,'04_ROI_AUDIT'!B:B,B2,'04_ROI_AUDIT'!L:L,TRUE) -> 0 | C4: Hours saved for included rows in the selected month.
A5: gross_cost_avoidance_mtd | B5: =SUMIFS('04_ROI_AUDIT'!K:K,'04_ROI_AUDIT'!B:B,B2,'04_ROI_AUDIT'!L:L,TRUE) -> 0 | C5: Gross labor-cost avoidance for the selected month.
A6: operating_cost_mtd | B6: =SUM('05_INVESTMENT'!F:F) -> 0 | C6: Recurring monthly operating cost.
A7: one_time_cost_total | B7: =SUM('05_INVESTMENT'!G:G) -> 0 | C7: One-time implementation and enablement cost.
A8: net_benefit_mtd | B8: =B5-B6 -> 0 | C8: Gross cost avoidance minus monthly operating cost.
A9: annualized_net_benefit | B9: =B8*12 -> 0 | C9: Simple annualization of the current month net benefit.
A10: roi_percent | B10: =IF((B6*12+B7)=0,"",(B5*12-(B6*12+B7))/(B6*12+B7)) -> 0 | C10: Net ROI after recurring and one-time cost.
A11: payback_months | B11: =IF(B8<=0,"",B7/B8) | C11: Months required to recover one-time investment.
A12: top_agent_note | B12: Build a pivot table from 04_ROI_AUDIT grouped by task_id or agent_persona | C12: Charts are best added after upload to Google Sheets.
A13: excluded_rows | B13: =COUNTIF('04_ROI_AUDIT'!L:L,FALSE) -> 0 | C13: Rows excluded from ROI due to missing evidence, failed status, or missing baseline support.
